MANIFEST.in
README.txt
setup.cfg
setup.py
collective/__init__.py
collective.bulksharing.egg-info/PKG-INFO
collective.bulksharing.egg-info/SOURCES.txt
collective.bulksharing.egg-info/dependency_links.txt
collective.bulksharing.egg-info/entry_points.txt
collective.bulksharing.egg-info/namespace_packages.txt
collective.bulksharing.egg-info/not-zip-safe
collective.bulksharing.egg-info/requires.txt
collective.bulksharing.egg-info/top_level.txt
collective/bulksharing/__init__.py
collective/bulksharing/configure.zcml
collective/bulksharing/profiles.zcml
collective/bulksharing/browser/__init__.py
collective/bulksharing/browser/bulksharing.pt
collective/bulksharing/browser/bulksharing.py
collective/bulksharing/browser/configure.zcml
collective/bulksharing/browser/table.pt
collective/bulksharing/profiles/default/actions.xml
collective/bulksharing/tests/__init__.py
collective/bulksharing/tests/base.py
collective/bulksharing/tests/bulksharing_view.txt
collective/bulksharing/tests/test_functional.py
docs/HISTORY.txt
docs/LICENSE.GPL
docs/LICENSE.txt