Metadata-Version: 1.0
Name: collective.bulksharing
Version: 1.0
Summary: This packages allows setting local roles for multiple items inside folder in one run.
Home-page: https://github.com/vipod/collective.bulksharing
Author: Vitaliy Podoba
Author-email: vitaliypodoba@gmail.com
License: GPL
Platform: UNKNOWN
Classifier: Programming Language :: Python
